wagtailosm/__init__.py
wagtailosm/wagtail_hooks.py
wagtailosm/static/wagtailosm/css/wagtailadmin.css
wagtailosm-0.4.0.dist-info/METADATA
wagtailosm-0.4.0.dist-info/WHEEL
wagtailosm-0.4.0.dist-info/entry_points.txt
wagtailosm-0.4.0.dist-info/licenses/LICENSE
wagtailosm-0.4.0.dist-info/RECORD
