Metadata-Version: 2.4
Name: wagtailosm
Version: 0.4.0
Summary: Open Street Map integration for Wagtail
Author-email: bbb <benjamin@overtag.dk>
License-File: LICENSE
Requires-Python: >=3.10
Requires-Dist: django-osm-field>=0.6.0
Requires-Dist: wagtail>=5.2
Requires-Dist: wheel>=0.22
